krenamer/__init__.py
krenamer/core.py
krenamer/gui.py
krenamer/main.py
krenamer-1.0.0.dist-info/licenses/LICENSE
krenamer-1.0.0.dist-info/METADATA
krenamer-1.0.0.dist-info/WHEEL
krenamer-1.0.0.dist-info/entry_points.txt
krenamer-1.0.0.dist-info/top_level.txt
krenamer-1.0.0.dist-info/RECORD
