Metadata-Version: 2.4
Name: krenamer
Version: 1.0.0
Summary: Korean Windows GUI file renamer tool with drag & drop functionality
Author-email: Euiyun Kim <geniuskey@gmail.com>
License: MIT
Project-URL: Homepage, https://github.com/geniuskey/krenamer
Project-URL: Documentation, https://geniuskey.github.io/krenamer
Project-URL: Repository, https://github.com/geniuskey/krenamer
Classifier: Programming Language :: Python :: 3
Classifier: License :: OSI Approved :: MIT License
Classifier: Operating System :: Microsoft :: Windows
Classifier: Development Status :: 4 - Beta
Classifier: Intended Audience :: End Users/Desktop
Classifier: Topic :: System :: Filesystems
Classifier: Topic :: Utilities
Classifier: Natural Language :: Korean
Requires-Python: >=3.8
License-File: LICENSE
Requires-Dist: tkinterdnd2>=0.3.0
Provides-Extra: dev
Requires-Dist: pyinstaller>=5.0; extra == "dev"
Requires-Dist: build; extra == "dev"
Requires-Dist: twine; extra == "dev"
Requires-Dist: mkdocs; extra == "dev"
Requires-Dist: mkdocs-material; extra == "dev"
Requires-Dist: mkdocs-minify-plugin; extra == "dev"
Requires-Dist: pymdown-extensions; extra == "dev"
Requires-Dist: pytest; extra == "dev"
Dynamic: license-file
